CHANGELOG.md
missouri/__init__.py
missouri/coding.py
missouri/json.py
missouri/numpylib.py
missouri/openlib.py
missouri/py.typed
missouri-1.0.0.dist-info/LICENSE
missouri-1.0.0.dist-info/WHEEL
missouri-1.0.0.dist-info/METADATA
missouri-1.0.0.dist-info/RECORD
