Metadata-Version: 2.1
Name: missouri
Version: 1.0.0
Summary: Read and write JSON in one line
Home-page: https://github.com/metabolize/missouri
License: Apache-2.0
Author: Paul Melnikow
Author-email: github@paulmelnikow.com
Requires-Python: >=3.9,<4
Classifier: Development Status :: 5 - Production/Stable
Classifier: Intended Audience :: Developers
Classifier: License :: OSI Approved :: Apache Software License
Classifier: Operating System :: OS Independent
Classifier: Programming Language :: Python :: 3
Classifier: Programming Language :: Python :: 3.9
Classifier: Programming Language :: Python :: 3.10
Classifier: Programming Language :: Python :: 3.11
Classifier: Topic :: Utilities
Classifier: Typing :: Typed
Requires-Dist: simplejson (>=3,<4)
Project-URL: Repository, https://github.com/metabolize/missouri
